LICENSE.txt
README.md
setup.py
django_elasticindex.egg-info/PKG-INFO
django_elasticindex.egg-info/SOURCES.txt
django_elasticindex.egg-info/dependency_links.txt
django_elasticindex.egg-info/requires.txt
django_elasticindex.egg-info/top_level.txt
elasticindex/__init__.py
elasticindex/client.py
elasticindex/fields.py
elasticindex/managers.py
elasticindex/models.py