Metadata-Version: 2.1
Name: django-elasticindex
Version: 0.2.2
Summary: Shallow elasticsearch wrapper on Django
Home-page: https://github.com/ytyng/django-elasticindex
Author: ytyng
Author-email: ytyng@live.jp
License: BSD
Keywords: Elasticsearch,Django,Python
Platform: UNKNOWN
